{
  "symbol": "DECK",
  "name": "Deckers Brands",
  "sector": "Consumer Discretionary",
  "industry": "Footwear",
  "date_added": "2024-03-18",
  "headquarters": "Goleta, California",
  "founded": "1973",
  "market_cap": 15774.464,
  "pe_ratio": 16.676146,
  "forward_pe": 16.597483,
  "eps": 6.33,
  "revenue": 4985.611776,
  "profit_margin": 0.19378,
  "debt_to_equity": 11.022,
  "return_on_equity": 0.41818002,
  "dividend_yield": null,
  "current_price": 105.55999755859375,
  "year_high": 223.97999572753906,
  "year_low": 93.72000122070312,
  "price_change_1d": 0.2564314186710101,
  "price_change_1w": 0.1517988903212301,
  "price_change_1m": -2.548007887745912,
  "description": "Deckers Outdoor Corporation, together with its subsidiaries, designs, markets, and distributes footwear, apparel, and accessories for casual lifestyle use and high-performance activities in the United States and internationally. The company offers premium footwear, apparel, and accessories under the UGG brand name; footwear, such as running, trail, hiking, fitness, and lifestyle shoes, as well as apparel and accessories under the HOKA brand name; and sandals, shoes, and boots under the Teva brand name. It also provides a casual footwear fashion line under the Koolaburra brand name; and footwear products under the AHNU brand name. The company sells its products through domestic and international retailers, international distributors, and dir",
  "website": "https://www.deckers.com",
  "employees": 5500,
  "exchange": "NYQ",
  "currency": "USD",
  "analyst_target_price": 127.32429,
  "recommendation": null,
  "number_of_analysts": 21,
  "earnings_history": [],
  "analyst_data": {
    "target_high": 169.0,
    "target_low": 100.0,
    "target_mean": 127.32429,
    "target_median": 127.0
  },
  "last_updated": "2025-07-09T11:20:10.739140",
  "data_quality": {
    "has_financial_data": true,
    "has_earnings_data": false,
    "has_analyst_data": true,
    "completeness_score": 0.6666666666666666
  }
}