{
  "symbol": "DIS",
  "company_name": "The Walt Disney Company",
  "sector": "Communication Services",
  "sub_sector": "Entertainment",
  "historical_reports": [
    {
      "symbol": "DIS",
      "earnings_date": "2025-07-19",
      "quarter": 3,
      "year": 2025,
      "actual_eps": 2.57,
      "estimated_eps": 2.23,
      "beat_miss_meet": "BEAT",
      "surprise_percent": 15.25,
      "revenue_billions": 79.35,
      "revenue_growth_percent": 4.5,
      "consensus_rating": "Buy",
      "confidence_score": 1.0,
      "source_url": "https://www.nasdaq.com/market-activity/stocks/dis/earnings",
      "data_verified_date": "2025-07-19",
      "stock_price_on_date": 160.93,
      "announcement_time": "BMO",
      "volume": 55142142,
      "date_earnings_report": "2025-07-19",
      "market_cap": 2574.88,
      "price_at_close_earnings_report_date": 160.93,
      "price_at_open_day_after_earnings_report_date": 169.04,
      "percentage_stock_change": 5.04,
      "earnings_report_result": "BEAT",
      "estimated_earnings_per_share": 2.23,
      "reported_earnings_per_share": 2.57,
      "volume_day_of_earnings_report": 55142142,
      "volume_day_after_earnings_report": 55061278,
      "moving_avg_200_day": 149.6,
      "moving_avg_50_day": 170.26,
      "week_52_high": 221.65,
      "week_52_low": 88.34,
      "market_sector": "Communication Services",
      "market_sub_sector": "Entertainment",
      "percentage_short_interest": 3.61,
      "dividend_yield": 1.49,
      "ex_dividend_date": "2025-07-30"
    },
    {
      "symbol": "DIS",
      "earnings_date": "2025-04-20",
      "quarter": 2,
      "year": 2025,
      "actual_eps": 1.51,
      "estimated_eps": 1.78,
      "beat_miss_meet": "MISS",
      "surprise_percent": -15.17,
      "revenue_billions": 114.02,
      "revenue_growth_percent": -2.7,
      "consensus_rating": "Buy",
      "confidence_score": 1.0,
      "source_url": "https://www.nasdaq.com/market-activity/stocks/dis/earnings",
      "data_verified_date": "2025-07-19",
      "stock_price_on_date": 158.79,
      "announcement_time": "AMC",
      "volume": 71687617,
      "date_earnings_report": "2025-04-20",
      "market_cap": 2540.64,
      "price_at_close_earnings_report_date": 158.79,
      "price_at_open_day_after_earnings_report_date": 150.87,
      "percentage_stock_change": -4.99,
      "earnings_report_result": "MISS",
      "estimated_earnings_per_share": 1.78,
      "reported_earnings_per_share": 1.51,
      "volume_day_of_earnings_report": 71687617,
      "volume_day_after_earnings_report": 30351485,
      "moving_avg_200_day": 161.49,
      "moving_avg_50_day": 174.65,
      "week_52_high": 187.0,
      "week_52_low": 98.06,
      "market_sector": "Communication Services",
      "market_sub_sector": "Entertainment",
      "percentage_short_interest": 2.3,
      "dividend_yield": 1.05,
      "ex_dividend_date": "2025-05-26"
    },
    {
      "symbol": "DIS",
      "earnings_date": "2025-01-20",
      "quarter": 1,
      "year": 2025,
      "actual_eps": 0.78,
      "estimated_eps": 0.66,
      "beat_miss_meet": "BEAT",
      "surprise_percent": 18.18,
      "revenue_billions": 190.08,
      "revenue_growth_percent": -4.9,
      "consensus_rating": "Buy",
      "confidence_score": 1.0,
      "source_url": "https://www.nasdaq.com/market-activity/stocks/dis/earnings",
      "data_verified_date": "2025-07-19",
      "stock_price_on_date": 282.14,
      "announcement_time": "BMO",
      "volume": 44826625,
      "date_earnings_report": "2025-01-20",
      "market_cap": 4514.24,
      "price_at_close_earnings_report_date": 282.14,
      "price_at_open_day_after_earnings_report_date": 286.4,
      "percentage_stock_change": 1.51,
      "earnings_report_result": "BEAT",
      "estimated_earnings_per_share": 0.66,
      "reported_earnings_per_share": 0.78,
      "volume_day_of_earnings_report": 44826625,
      "volume_day_after_earnings_report": 41881816,
      "moving_avg_200_day": 319.98,
      "moving_avg_50_day": 297.95,
      "week_52_high": 317.76,
      "week_52_low": 165.28,
      "market_sector": "Communication Services",
      "market_sub_sector": "Entertainment",
      "percentage_short_interest": 4.71,
      "dividend_yield": 1.97,
      "ex_dividend_date": "2025-02-25"
    },
    {
      "symbol": "DIS",
      "earnings_date": "2024-10-22",
      "quarter": 4,
      "year": 2024,
      "actual_eps": 1.81,
      "estimated_eps": 1.38,
      "beat_miss_meet": "BEAT",
      "surprise_percent": 31.16,
      "revenue_billions": 97.6,
      "revenue_growth_percent": -0.7,
      "consensus_rating": "Sell",
      "confidence_score": 1.0,
      "source_url": "https://www.nasdaq.com/market-activity/stocks/dis/earnings",
      "data_verified_date": "2025-07-19",
      "stock_price_on_date": 151.09,
      "announcement_time": "AMC",
      "volume": 46864109,
      "date_earnings_report": "2024-10-22",
      "market_cap": 2417.44,
      "price_at_close_earnings_report_date": 151.09,
      "price_at_open_day_after_earnings_report_date": 153.43,
      "percentage_stock_change": 1.55,
      "earnings_report_result": "BEAT",
      "estimated_earnings_per_share": 1.38,
      "reported_earnings_per_share": 1.81,
      "volume_day_of_earnings_report": 46864109,
      "volume_day_after_earnings_report": 42100521,
      "moving_avg_200_day": 144.92,
      "moving_avg_50_day": 158.75,
      "week_52_high": 209.69,
      "week_52_low": 106.96,
      "market_sector": "Communication Services",
      "market_sub_sector": "Entertainment",
      "percentage_short_interest": 4.3,
      "dividend_yield": 0.94,
      "ex_dividend_date": "2024-11-14"
    }
  ],
  "projected_reports": [
    {
      "symbol": "DIS",
      "earnings_date": "2025-10-17",
      "quarter": 4,
      "year": 2025,
      "actual_eps": null,
      "estimated_eps": 1.84,
      "beat_miss_meet": "PROJECTED",
      "surprise_percent": null,
      "revenue_billions": null,
      "revenue_growth_percent": null,
      "consensus_rating": "Buy",
      "confidence_score": 0.7,
      "source_url": "https://www.nasdaq.com/market-activity/stocks/dis/earnings",
      "data_verified_date": "2025-07-19",
      "stock_price_on_date": 230.08,
      "announcement_time": "AMC",
      "volume": 41919765,
      "date_earnings_report": "2025-10-17",
      "market_cap": 3681.28,
      "price_at_close_earnings_report_date": null,
      "price_at_open_day_after_earnings_report_date": null,
      "percentage_stock_change": null,
      "earnings_report_result": "PROJECTED",
      "estimated_earnings_per_share": 1.84,
      "reported_earnings_per_share": null,
      "volume_day_of_earnings_report": null,
      "volume_day_after_earnings_report": null,
      "moving_avg_200_day": 237.64,
      "moving_avg_50_day": 249.49,
      "week_52_high": 322.81,
      "week_52_low": 131.38,
      "market_sector": "Communication Services",
      "market_sub_sector": "Entertainment",
      "percentage_short_interest": 2.39,
      "dividend_yield": 0.13,
      "ex_dividend_date": "2025-11-15"
    },
    {
      "symbol": "DIS",
      "earnings_date": "2026-01-15",
      "quarter": 1,
      "year": 2026,
      "actual_eps": null,
      "estimated_eps": 1.66,
      "beat_miss_meet": "PROJECTED",
      "surprise_percent": null,
      "revenue_billions": null,
      "revenue_growth_percent": null,
      "consensus_rating": "Buy",
      "confidence_score": 0.7,
      "source_url": "https://www.nasdaq.com/market-activity/stocks/dis/earnings",
      "data_verified_date": "2025-07-19",
      "stock_price_on_date": 244.83,
      "announcement_time": "BMO",
      "volume": 36303771,
      "date_earnings_report": "2026-01-15",
      "market_cap": 3917.28,
      "price_at_close_earnings_report_date": null,
      "price_at_open_day_after_earnings_report_date": null,
      "percentage_stock_change": null,
      "earnings_report_result": "PROJECTED",
      "estimated_earnings_per_share": 1.66,
      "reported_earnings_per_share": null,
      "volume_day_of_earnings_report": null,
      "volume_day_after_earnings_report": null,
      "moving_avg_200_day": 217.94,
      "moving_avg_50_day": 265.47,
      "week_52_high": 366.22,
      "week_52_low": 198.08,
      "market_sector": "Communication Services",
      "market_sub_sector": "Entertainment",
      "percentage_short_interest": 3.26,
      "dividend_yield": 1.78,
      "ex_dividend_date": "2026-02-15"
    }
  ],
  "last_updated": "2025-07-19T18:46:13.820709",
  "data_source": "nasdaq.com"
}