{
  "symbol": "RVTY",
  "company_name": "Revvity, Inc.",
  "sector": "Healthcare",
  "sub_sector": "Diagnostics & Research",
  "historical_reports": [
    {
      "symbol": "RVTY",
      "earnings_date": "2025-07-19",
      "quarter": 3,
      "year": 2025,
      "actual_eps": 0.97,
      "estimated_eps": 0.85,
      "beat_miss_meet": "BEAT",
      "surprise_percent": 14.12,
      "revenue_billions": 173.77,
      "revenue_growth_percent": 11.8,
      "consensus_rating": "Sell",
      "confidence_score": 1.0,
      "source_url": "https://www.nasdaq.com/market-activity/stocks/rvty/earnings",
      "data_verified_date": "2025-07-19",
      "stock_price_on_date": 151.96,
      "announcement_time": "AMC",
      "volume": 50973800,
      "date_earnings_report": "2025-07-19",
      "market_cap": 2431.36,
      "price_at_close_earnings_report_date": 151.96,
      "price_at_open_day_after_earnings_report_date": 142.86,
      "percentage_stock_change": -5.99,
      "earnings_report_result": "BEAT",
      "estimated_earnings_per_share": 0.85,
      "reported_earnings_per_share": 0.97,
      "volume_day_of_earnings_report": 50973800,
      "volume_day_after_earnings_report": 22995826,
      "moving_avg_200_day": 132.85,
      "moving_avg_50_day": 161.12,
      "week_52_high": 169.32,
      "week_52_low": 91.77,
      "market_sector": "Healthcare",
      "market_sub_sector": "Diagnostics & Research",
      "percentage_short_interest": 2.53,
      "dividend_yield": 3.33,
      "ex_dividend_date": "2025-08-09"
    },
    {
      "symbol": "RVTY",
      "earnings_date": "2025-04-20",
      "quarter": 2,
      "year": 2025,
      "actual_eps": 1.95,
      "estimated_eps": 2.24,
      "beat_miss_meet": "MISS",
      "surprise_percent": -12.95,
      "revenue_billions": 171.06,
      "revenue_growth_percent": 10.3,
      "consensus_rating": "Hold",
      "confidence_score": 1.0,
      "source_url": "https://www.nasdaq.com/market-activity/stocks/rvty/earnings",
      "data_verified_date": "2025-07-19",
      "stock_price_on_date": 106.43,
      "announcement_time": "AMC",
      "volume": 48914984,
      "date_earnings_report": "2025-04-20",
      "market_cap": 1702.88,
      "price_at_close_earnings_report_date": 106.43,
      "price_at_open_day_after_earnings_report_date": 116.5,
      "percentage_stock_change": 9.46,
      "earnings_report_result": "MISS",
      "estimated_earnings_per_share": 2.24,
      "reported_earnings_per_share": 1.95,
      "volume_day_of_earnings_report": 48914984,
      "volume_day_after_earnings_report": 25402841,
      "moving_avg_200_day": 119.44,
      "moving_avg_50_day": 97.73,
      "week_52_high": 136.93,
      "week_52_low": 61.85,
      "market_sector": "Healthcare",
      "market_sub_sector": "Diagnostics & Research",
      "percentage_short_interest": 1.42,
      "dividend_yield": 3.59,
      "ex_dividend_date": "2025-05-08"
    },
    {
      "symbol": "RVTY",
      "earnings_date": "2025-01-20",
      "quarter": 1,
      "year": 2025,
      "actual_eps": 2.45,
      "estimated_eps": 2.54,
      "beat_miss_meet": "MISS",
      "surprise_percent": -3.54,
      "revenue_billions": 181.3,
      "revenue_growth_percent": 8.5,
      "consensus_rating": "Buy",
      "confidence_score": 1.0,
      "source_url": "https://www.nasdaq.com/market-activity/stocks/rvty/earnings",
      "data_verified_date": "2025-07-19",
      "stock_price_on_date": 279.01,
      "announcement_time": "AMC",
      "volume": 38015006,
      "date_earnings_report": "2025-01-20",
      "market_cap": 4464.16,
      "price_at_close_earnings_report_date": 279.01,
      "price_at_open_day_after_earnings_report_date": 274.63,
      "percentage_stock_change": -1.57,
      "earnings_report_result": "MISS",
      "estimated_earnings_per_share": 2.54,
      "reported_earnings_per_share": 2.45,
      "volume_day_of_earnings_report": 38015006,
      "volume_day_after_earnings_report": 48162169,
      "moving_avg_200_day": 277.0,
      "moving_avg_50_day": 298.14,
      "week_52_high": 389.89,
      "week_52_low": 215.72,
      "market_sector": "Healthcare",
      "market_sub_sector": "Diagnostics & Research",
      "percentage_short_interest": 4.09,
      "dividend_yield": 3.87,
      "ex_dividend_date": "2025-02-17"
    },
    {
      "symbol": "RVTY",
      "earnings_date": "2024-10-22",
      "quarter": 4,
      "year": 2024,
      "actual_eps": 0.66,
      "estimated_eps": 0.82,
      "beat_miss_meet": "MISS",
      "surprise_percent": -19.51,
      "revenue_billions": 199.43,
      "revenue_growth_percent": -2.9,
      "consensus_rating": "Sell",
      "confidence_score": 1.0,
      "source_url": "https://www.nasdaq.com/market-activity/stocks/rvty/earnings",
      "data_verified_date": "2025-07-19",
      "stock_price_on_date": 108.69,
      "announcement_time": "BMO",
      "volume": 37875062,
      "date_earnings_report": "2024-10-22",
      "market_cap": 1739.04,
      "price_at_close_earnings_report_date": 108.69,
      "price_at_open_day_after_earnings_report_date": 102.18,
      "percentage_stock_change": -5.99,
      "earnings_report_result": "MISS",
      "estimated_earnings_per_share": 0.82,
      "reported_earnings_per_share": 0.66,
      "volume_day_of_earnings_report": 37875062,
      "volume_day_after_earnings_report": 17717707,
      "moving_avg_200_day": 106.99,
      "moving_avg_50_day": 108.61,
      "week_52_high": 139.09,
      "week_52_low": 94.87,
      "market_sector": "Healthcare",
      "market_sub_sector": "Diagnostics & Research",
      "percentage_short_interest": 3.86,
      "dividend_yield": 1.62,
      "ex_dividend_date": "2024-11-22"
    }
  ],
  "projected_reports": [
    {
      "symbol": "RVTY",
      "earnings_date": "2025-10-17",
      "quarter": 4,
      "year": 2025,
      "actual_eps": null,
      "estimated_eps": 2.09,
      "beat_miss_meet": "PROJECTED",
      "surprise_percent": null,
      "revenue_billions": null,
      "revenue_growth_percent": null,
      "consensus_rating": "Hold",
      "confidence_score": 0.7,
      "source_url": "https://www.nasdaq.com/market-activity/stocks/rvty/earnings",
      "data_verified_date": "2025-07-19",
      "stock_price_on_date": 248.05,
      "announcement_time": "AMC",
      "volume": 38979056,
      "date_earnings_report": "2025-10-17",
      "market_cap": 3968.8,
      "price_at_close_earnings_report_date": null,
      "price_at_open_day_after_earnings_report_date": null,
      "percentage_stock_change": null,
      "earnings_report_result": "PROJECTED",
      "estimated_earnings_per_share": 2.09,
      "reported_earnings_per_share": null,
      "volume_day_of_earnings_report": null,
      "volume_day_after_earnings_report": null,
      "moving_avg_200_day": 254.42,
      "moving_avg_50_day": 252.32,
      "week_52_high": 330.04,
      "week_52_low": 211.59,
      "market_sector": "Healthcare",
      "market_sub_sector": "Diagnostics & Research",
      "percentage_short_interest": 4.39,
      "dividend_yield": 1.01,
      "ex_dividend_date": "2025-11-21"
    },
    {
      "symbol": "RVTY",
      "earnings_date": "2026-01-15",
      "quarter": 1,
      "year": 2026,
      "actual_eps": null,
      "estimated_eps": 1.41,
      "beat_miss_meet": "PROJECTED",
      "surprise_percent": null,
      "revenue_billions": null,
      "revenue_growth_percent": null,
      "consensus_rating": "Buy",
      "confidence_score": 0.7,
      "source_url": "https://www.nasdaq.com/market-activity/stocks/rvty/earnings",
      "data_verified_date": "2025-07-19",
      "stock_price_on_date": 112.86,
      "announcement_time": "AMC",
      "volume": 31671725,
      "date_earnings_report": "2026-01-15",
      "market_cap": 1805.76,
      "price_at_close_earnings_report_date": null,
      "price_at_open_day_after_earnings_report_date": null,
      "percentage_stock_change": null,
      "earnings_report_result": "PROJECTED",
      "estimated_earnings_per_share": 1.41,
      "reported_earnings_per_share": null,
      "volume_day_of_earnings_report": null,
      "volume_day_after_earnings_report": null,
      "moving_avg_200_day": 114.72,
      "moving_avg_50_day": 106.97,
      "week_52_high": 128.47,
      "week_52_low": 66.94,
      "market_sector": "Healthcare",
      "market_sub_sector": "Diagnostics & Research",
      "percentage_short_interest": 1.26,
      "dividend_yield": 3.09,
      "ex_dividend_date": "2026-01-25"
    }
  ],
  "last_updated": "2025-07-19T16:41:20.069942",
  "data_source": "nasdaq.com"
}